{
  "ComponentIndexes": {
    "Accessibility Helpers": 7,
    "Accessibility Helpers_1": 12,
    "Accessibility Helpers_3": 12,
    "Flags": 10,
    "Flags_1": 10,
    "PP-Header": 6,
    "PP-Header_1": 12,
    "PP-Header_2": 12,
    "PP-hIconBar": 9,
    "PP-hIconBar_1": 10,
    "PP-MainMenu": 3,
    "PP-MainMenu_1": 2,
    "PP-OfficeRail": 5,
    "PP-OfficeRail_1": 4,
    "PP-TeamsRail": 4,
    "PP-TeamsRail_1": 3,
    "PP-vIconBar": 8,
    "PP-vIconBar_1": 9,
    "TM-MainMenu_1": 10,
    "VS Code": 11,
    "VS Code_1": 12
  },
  "ControlUniqueIds": {
    "_seperator": 6,
    "Accessibility Helpers": 22,
    "Accessibility Helpers_1": 284,
    "Accessibility Helpers_3": 247,
    "App": 1,
    "Arrow1": 131,
    "back_B_3": 220,
    "back_G_3": 216,
    "back_R_3": 208,
    "Background Color_3": 241,
    "Button1_1": 80,
    "Button2": 235,
    "Button3": 282,
    "Button3_1": 283,
    "Button4": 278,
    "Button4_1": 128,
    "Button4_2": 271,
    "Button5_6": 50,
    "Button6": 281,
    "Button6_1": 286,
    "Button7": 20,
    "CanvasFileDownloader1": 234,
    "CanvasFileUpload": 236,
    "Circle3_1": 84,
    "con_Accessibility_Home": 201,
    "con_Footer_Home": 243,
    "con_Footer_Home_1": 104,
    "con_Header_Home": 137,
    "con_Header_Home_1": 42,
    "con_Main_home": 150,
    "con_MainHeader_Home": 147,
    "con_MainWindow_Home": 146,
    "con_Menu_Home": 143,
    "Flags": 37,
    "Flags_1": 138,
    "gal_Bootstrap_home": 181,
    "gal_Feather_home": 186,
    "gal_fluentui_home": 196,
    "gal_FontAwesome_home": 161,
    "gal_hIconBar": 28,
    "gal_iconic_home": 156,
    "gal_MaterialDesign_home": 176,
    "gal_Menu": 32,
    "gal_Menu_1": 10,
    "gal_Menu_2": 16,
    "gal_MicrosoftIcons": 151,
    "gal_MonoIcons_home": 191,
    "gal_MSMenu": 74,
    "gal_Octicons_home": 171,
    "gal_SimpleIcons_home": 166,
    "gal_vIconBar": 24,
    "Gallery1": 273,
    "Gallery1_1": 107,
    "Gallery1_2": 248,
    "Gallery2_1": 82,
    "galleryTemplate1": 274,
    "galleryTemplate1_1": 108,
    "galleryTemplate1_2": 249,
    "galleryTemplate2": 25,
    "galleryTemplate2_10": 182,
    "galleryTemplate2_11": 187,
    "galleryTemplate2_12": 192,
    "galleryTemplate2_3": 197,
    "galleryTemplate2_4": 157,
    "galleryTemplate2_5": 152,
    "galleryTemplate2_6": 162,
    "galleryTemplate2_7": 167,
    "galleryTemplate2_8": 172,
    "galleryTemplate2_9": 177,
    "galleryTemplate3": 29,
    "galleryTemplate4_1": 33,
    "galleryTemplate4_2": 11,
    "galleryTemplate4_3": 17,
    "galleryTemplate4_4": 83,
    "galleryTemplate5_1": 75,
    "Group1": 132,
    "Group2_1": 242,
    "h_inpSize": 71,
    "Home": 136,
    "icon": 35,
    "icon_1": 13,
    "icon_2": 21,
    "icon_B_3": 222,
    "icon_G_3": 215,
    "icon_Next": 36,
    "icon_Next_2": 81,
    "icon_R_3": 210,
    "Icon1": 145,
    "Icon10": 103,
    "Icon12": 130,
    "Icon12_1": 285,
    "Icon2": 142,
    "Icon2_1": 44,
    "Icon3": 239,
    "Icon4": 279,
    "Icon4_1": 129,
    "Icon4_2": 115,
    "Icon4_3": 256,
    "Icon4_4": 272,
    "Icon6": 69,
    "Icon6_1": 66,
    "Icon7": 111,
    "Icon7_1": 252,
    "Icon8": 110,
    "Icon8_1": 251,
    "Icon9_4": 259,
    "Icon9_5": 260,
    "iconImageData": 238,
    "Image1": 275,
    "Image1_1": 4,
    "Image1_2": 113,
    "Image1_3": 114,
    "Image1_4": 254,
    "Image1_5": 255,
    "Image2": 40,
    "Image3_1": 85,
    "Image4": 8,
    "Image4_1": 79,
    "img_Icon": 26,
    "img_Icon_1": 30,
    "imgIconOFI_10": 184,
    "imgIconOFI_11": 189,
    "imgIconOFI_12": 194,
    "imgIconOFI_3": 199,
    "imgIconOFI_4": 159,
    "imgIconOFI_5": 154,
    "imgIconOFI_6": 164,
    "imgIconOFI_7": 169,
    "imgIconOFI_8": 174,
    "imgIconOFI_9": 179,
    "inp_BackgroundColor_home": 207,
    "inp_Color_home": 206,
    "inp_Menutext": 276,
    "inp_Menutext_1": 277,
    "inp_Menutext_2": 119,
    "inp_Menutext_3": 121,
    "inp_Menutext_4": 125,
    "inp_Menutext_5": 123,
    "inp_Menutext_6": 262,
    "inp_Menutext_7": 264,
    "inp_Menutext_8": 266,
    "inp_Menutext_9": 268,
    "inp_Search_home": 149,
    "inp_vSize": 70,
    "input_CollectionName": 48,
    "Label1": 148,
    "Label10_1": 78,
    "Label12": 118,
    "Label12_1": 120,
    "Label12_10": 258,
    "Label12_11": 261,
    "Label12_12": 263,
    "Label12_13": 265,
    "Label12_14": 267,
    "Label12_15": 269,
    "Label12_2": 124,
    "Label12_3": 126,
    "Label12_4": 112,
    "Label12_5": 116,
    "Label12_6": 117,
    "Label12_7": 122,
    "Label12_8": 253,
    "Label12_9": 257,
    "Label13": 60,
    "Label13_1": 63,
    "Label13_2": 54,
    "Label13_3": 55,
    "Label13_4": 51,
    "Label13_5": 52,
    "Label13_6": 56,
    "Label13_7": 57,
    "Label14": 90,
    "Label14_1": 92,
    "Label14_10": 68,
    "Label14_11": 73,
    "Label14_12": 98,
    "Label14_13": 99,
    "Label14_2": 91,
    "Label14_3": 93,
    "Label14_4": 94,
    "Label14_5": 101,
    "Label14_6": 95,
    "Label14_7": 102,
    "Label14_8": 67,
    "Label14_9": 72,
    "Label2": 280,
    "Label2_1": 106,
    "Label2_2": 246,
    "Label3": 141,
    "Label3_1": 45,
    "Label6": 49,
    "LabelsInputs": 134,
    "lbl_BackGroundLuminance_12": 233,
    "lbl_BackGroundLuminance_13": 229,
    "lbl_BackGroundLuminance_14": 228,
    "lbl_BackGroundLuminance_15": 226,
    "lbl_ContrastRatio_3": 232,
    "lbl_IconColorLuminance_3": 227,
    "lbl_IconName": 203,
    "lbl_MenuText": 34,
    "lbl_MenuText_1": 14,
    "lbl_PowerApps": 5,
    "lbl_ScreenName": 7,
    "lblIconColorOFI_10": 205,
    "lblIconColorOFI_11": 204,
    "lblIconColorOFI_46": 223,
    "lblIconColorOFI_47": 218,
    "lblIconColorOFI_48": 211,
    "lblIconColorOFI_49": 209,
    "lblIconColorOFI_50": 214,
    "lblIconColorOFI_51": 221,
    "lblIconColorOFI_9": 231,
    "lblIconImageDataOFI_4": 237,
    "lblIconNameOFI_10": 185,
    "lblIconNameOFI_11": 190,
    "lblIconNameOFI_12": 195,
    "lblIconNameOFI_3": 200,
    "lblIconNameOFI_4": 160,
    "lblIconNameOFI_5": 155,
    "lblIconNameOFI_6": 165,
    "lblIconNameOFI_7": 170,
    "lblIconNameOFI_8": 175,
    "lblIconNameOFI_9": 180,
    "lblSelectedIconOFI_26": 202,
    "Menu Builder": 41,
    "MicrosoftMenu": 133,
    "PCFCopyTextComponent2": 240,
    "PP-Header": 3,
    "PP-Header_1": 140,
    "PP-Header_2": 43,
    "PP-hIconBar": 27,
    "PP-hIconBar_1": 89,
    "PP-MainMenu": 31,
    "PP-MainMenu_1": 61,
    "PP-OfficeRail": 15,
    "PP-OfficeRail_1": 65,
    "PP-TeamsRail": 9,
    "PP-TeamsRail_1": 64,
    "PP-vIconBar": 23,
    "PP-vIconBar_1": 87,
    "Rectangle1": 244,
    "Rectangle1_1": 105,
    "Rectangle1_2": 245,
    "Rectangle2_10": 183,
    "Rectangle2_11": 188,
    "Rectangle2_12": 193,
    "Rectangle2_3": 198,
    "Rectangle2_4": 158,
    "Rectangle2_5": 153,
    "Rectangle2_6": 163,
    "Rectangle2_7": 168,
    "Rectangle2_8": 173,
    "Rectangle2_9": 178,
    "Rectangle3": 12,
    "Rectangle3_1": 18,
    "Rectangle3_2": 19,
    "Rectangle4_2": 77,
    "Rectangle4_3": 76,
    "Rectangle5": 58,
    "Rectangle6": 109,
    "Rectangle6_1": 250,
    "Rectangle7": 59,
    "Rectangle7_1": 62,
    "Rectangle8": 88,
    "Rectangle8_1": 86,
    "Screen1": 39,
    "selected_Icon": 230,
    "Slider_Background_B_3": 224,
    "Slider_Background_G_3": 219,
    "Slider_Background_R_3": 212,
    "Slider_Icon_B_3": 225,
    "Slider_Icon_G_3": 217,
    "Slider_Icon_R_3": 213,
    "TM-MainMenu_1": 144,
    "Toggle1": 127,
    "Toggle1_1": 270,
    "VS Code": 38,
    "VS Code_1": 139
  },
  "HeaderLastSavedDateTimeUTC": "05/03/2021 11:02:51",
  "LocalDatabaseReferencesAsEmpty": false,
  "LocalResourceFileNames": {
    "cropped-logo-red": "0002.png",
    "header": "0007.png"
  },
  "LocalResourceRootPaths": {
    "cropped-logo-red": "https://docserverpaaprodsuk.blob.core.windows.net/af06bd06-8d5a-4cdd-b64f-0efc0681e948-1/resource/Assets0Images00002.png?sv=2017-04-17&sr=b&sig=6HSDrvCNBz13K14COizZOZiro8fTJxFh%2BvvMR9IM4hs%3D&spr=https&se=2021-05-04T09%3A08%3A31Z&sp=r",
    "header": "https://docserverpaaprodsuk.blob.core.windows.net/af06bd06-8d5a-4cdd-b64f-0efc0681e948-1/resource/Assets0Images00007.png?sv=2017-04-17&sr=b&sig=8Uc%2F9OHcelvQQZN6nI7QyVFPSnm0mkT96iZIBEUSUGs%3D&spr=https&se=2021-05-04T09%3A08%3A31Z&sp=r"
  },
  "OldLogoFileName": "ubfx5llg.jpg",
  "OrderComponentMetadata": {
    "251d3182c5f14ebda0954caccc8061c6": 7,
    "2f6fd9479bf54d6d87804e13a7a46344": 2,
    "677fb63b9818481e87e97787923fb8da": 4,
    "6fda9d5d46344732b503488ec8d08939": 3,
    "8d5a6fce1ee2453e82777a553277693a": 1,
    "9f31274f2958450c8715bd6776b635c5": 5,
    "a437dfc8870647489d9b037db2a7427e": 0,
    "c855490e17ba4912a20655359782e195": 6,
    "e4882056a52441119876391294845a30": 8
  },
  "OrderComponentTemplate": {
    "251d3182c5f14ebda0954caccc8061c6": 7,
    "2f6fd9479bf54d6d87804e13a7a46344": 2,
    "677fb63b9818481e87e97787923fb8da": 4,
    "6fda9d5d46344732b503488ec8d08939": 3,
    "8d5a6fce1ee2453e82777a553277693a": 1,
    "9f31274f2958450c8715bd6776b635c5": 5,
    "a437dfc8870647489d9b037db2a7427e": 0,
    "c855490e17ba4912a20655359782e195": 6,
    "e4882056a52441119876391294845a30": 8
  },
  "OrderDataSource": {
    "Bootstrap": 6,
    "col_MainMenu_home": 19,
    "CustomGallerySample": 2,
    "DECtoHEX": 20,
    "Eva": 16,
    "Feather": 4,
    "featherIcons": 25,
    "FluentUI": 5,
    "FontAwesome": 8,
    "GameIcons": 17,
    "Iconic": 9,
    "MaterialDesign": 7,
    "menu": 26,
    "MenuItems": 22,
    "MSIcons": 18,
    "newMenu": 21,
    "NotoEmoji": 13,
    "Octicons": 11,
    "Office365Users": 1,
    "PowerAppsforMakers": 0,
    "PublicDomain": 15,
    "RadioSample": 3,
    "rowCounter": 23,
    "Simple": 10,
    "SuperTinyIcons": 12,
    "tempMenu": 24,
    "Weather": 14
  },
  "OrderGroupControls": {
    "Background Color_3": {
      "back_B_3": 7,
      "back_G_3": 8,
      "back_R_3": 9,
      "lbl_BackGroundLuminance_13": 10,
      "lbl_BackGroundLuminance_14": 11,
      "lblIconColorOFI_10": 0,
      "lblIconColorOFI_46": 1,
      "lblIconColorOFI_47": 2,
      "lblIconColorOFI_48": 3,
      "Slider_Background_B_3": 6,
      "Slider_Background_G_3": 5,
      "Slider_Background_R_3": 4
    },
    "Group1": {
      "PP-vIconBar_1": 1,
      "Rectangle8_1": 0
    },
    "Group2_1": {
      "icon_B_3": 9,
      "icon_G_3": 8,
      "icon_R_3": 7,
      "inp_Color_home": 3,
      "lbl_BackGroundLuminance_15": 11,
      "lbl_IconColorLuminance_3": 10,
      "lblIconColorOFI_11": 4,
      "lblIconColorOFI_49": 0,
      "lblIconColorOFI_50": 5,
      "lblIconColorOFI_51": 12,
      "Slider_Icon_B_3": 2,
      "Slider_Icon_G_3": 1,
      "Slider_Icon_R_3": 6
    },
    "LabelsInputs": {
      "Button5_6": 0,
      "h_inpSize": 11,
      "inp_vSize": 12,
      "input_CollectionName": 2,
      "Label13": 26,
      "Label13_1": 25,
      "Label13_2": 20,
      "Label13_3": 17,
      "Label13_4": 14,
      "Label13_5": 13,
      "Label13_6": 10,
      "Label13_7": 3,
      "Label14": 24,
      "Label14_1": 23,
      "Label14_10": 9,
      "Label14_11": 6,
      "Label14_12": 5,
      "Label14_13": 4,
      "Label14_2": 22,
      "Label14_3": 21,
      "Label14_4": 19,
      "Label14_5": 18,
      "Label14_6": 16,
      "Label14_7": 15,
      "Label14_8": 8,
      "Label14_9": 7,
      "Label6": 1
    },
    "MicrosoftMenu": {
      "gal_MSMenu": 2,
      "Icon6": 0,
      "Rectangle5": 1
    }
  },
  "OrderTemplate": {},
  "OrderXMLTemplate": {
    "arrow": 9,
    "button": 4,
    "circle": 7,
    "gallery": 6,
    "icon": 2,
    "image": 0,
    "label": 1,
    "rectangle": 5,
    "slider": 10,
    "text": 3,
    "toggleSwitch": 8
  },
  "PublishOrderIndices": {
    "_seperator": 256,
    "Accessibility Helpers": 0,
    "Accessibility Helpers_1": 147,
    "Accessibility Helpers_3": 110,
    "App": 0,
    "Arrow1": 236,
    "back_B_3": 85,
    "back_G_3": 81,
    "back_R_3": 73,
    "Background Color_3": 69,
    "Button1_1": 187,
    "Button2": 100,
    "Button3": 145,
    "Button3_1": 146,
    "Button4": 141,
    "Button4_1": 233,
    "Button4_2": 134,
    "Button5_6": 157,
    "Button6": 144,
    "Button6_1": 149,
    "Button7": 252,
    "CanvasFileDownloader1": 99,
    "CanvasFileUpload": 101,
    "Circle3_1": 191,
    "con_Accessibility_Home": 64,
    "con_Footer_Home": 106,
    "con_Footer_Home_1": 209,
    "con_Header_Home": 0,
    "con_Header_Home_1": 150,
    "con_Main_home": 13,
    "con_MainHeader_Home": 10,
    "con_MainWindow_Home": 9,
    "con_Menu_Home": 6,
    "Flags": 0,
    "Flags_1": 1,
    "gal_Bootstrap_home": 44,
    "gal_Feather_home": 49,
    "gal_fluentui_home": 59,
    "gal_FontAwesome_home": 24,
    "gal_hIconBar": 262,
    "gal_iconic_home": 19,
    "gal_MaterialDesign_home": 39,
    "gal_Menu": 238,
    "gal_Menu_1": 243,
    "gal_Menu_2": 248,
    "gal_MicrosoftIcons": 14,
    "gal_MonoIcons_home": 54,
    "gal_MSMenu": 181,
    "gal_Octicons_home": 34,
    "gal_SimpleIcons_home": 29,
    "gal_vIconBar": 259,
    "Gallery1": 136,
    "Gallery1_1": 212,
    "Gallery1_2": 111,
    "Gallery2_1": 189,
    "galleryTemplate1": 137,
    "galleryTemplate1_1": 213,
    "galleryTemplate1_2": 112,
    "galleryTemplate2": 260,
    "galleryTemplate2_10": 45,
    "galleryTemplate2_11": 50,
    "galleryTemplate2_12": 55,
    "galleryTemplate2_3": 60,
    "galleryTemplate2_4": 20,
    "galleryTemplate2_5": 15,
    "galleryTemplate2_6": 25,
    "galleryTemplate2_7": 30,
    "galleryTemplate2_8": 35,
    "galleryTemplate2_9": 40,
    "galleryTemplate3": 263,
    "galleryTemplate4_1": 239,
    "galleryTemplate4_2": 244,
    "galleryTemplate4_3": 249,
    "galleryTemplate4_4": 190,
    "galleryTemplate5_1": 182,
    "Group1": 195,
    "Group2_1": 67,
    "h_inpSize": 178,
    "Home": 0,
    "icon": 241,
    "icon_1": 246,
    "icon_2": 253,
    "icon_B_3": 87,
    "icon_G_3": 80,
    "icon_Next": 242,
    "icon_Next_2": 188,
    "icon_R_3": 75,
    "Icon1": 8,
    "Icon10": 208,
    "Icon12": 235,
    "Icon12_1": 148,
    "Icon2": 5,
    "Icon2_1": 152,
    "Icon3": 104,
    "Icon4": 142,
    "Icon4_1": 234,
    "Icon4_2": 220,
    "Icon4_3": 119,
    "Icon4_4": 135,
    "Icon6": 176,
    "Icon6_1": 173,
    "Icon7": 216,
    "Icon7_1": 115,
    "Icon8": 215,
    "Icon8_1": 114,
    "Icon9_4": 122,
    "Icon9_5": 123,
    "iconImageData": 103,
    "Image1": 138,
    "Image1_1": 254,
    "Image1_2": 218,
    "Image1_3": 219,
    "Image1_4": 117,
    "Image1_5": 118,
    "Image2": 237,
    "Image3_1": 192,
    "Image4": 258,
    "Image4_1": 186,
    "img_Icon": 261,
    "img_Icon_1": 264,
    "imgIconOFI_10": 47,
    "imgIconOFI_11": 52,
    "imgIconOFI_12": 57,
    "imgIconOFI_3": 62,
    "imgIconOFI_4": 22,
    "imgIconOFI_5": 17,
    "imgIconOFI_6": 27,
    "imgIconOFI_7": 32,
    "imgIconOFI_8": 37,
    "imgIconOFI_9": 42,
    "inp_BackgroundColor_home": 72,
    "inp_Color_home": 71,
    "inp_Menutext": 139,
    "inp_Menutext_1": 140,
    "inp_Menutext_2": 224,
    "inp_Menutext_3": 226,
    "inp_Menutext_4": 230,
    "inp_Menutext_5": 228,
    "inp_Menutext_6": 125,
    "inp_Menutext_7": 127,
    "inp_Menutext_8": 129,
    "inp_Menutext_9": 131,
    "inp_Search_home": 12,
    "inp_vSize": 177,
    "input_CollectionName": 155,
    "Label1": 11,
    "Label10_1": 185,
    "Label12": 223,
    "Label12_1": 225,
    "Label12_10": 121,
    "Label12_11": 124,
    "Label12_12": 126,
    "Label12_13": 128,
    "Label12_14": 130,
    "Label12_15": 132,
    "Label12_2": 229,
    "Label12_3": 231,
    "Label12_4": 217,
    "Label12_5": 221,
    "Label12_6": 222,
    "Label12_7": 227,
    "Label12_8": 116,
    "Label12_9": 120,
    "Label13": 167,
    "Label13_1": 170,
    "Label13_2": 160,
    "Label13_3": 161,
    "Label13_4": 158,
    "Label13_5": 159,
    "Label13_6": 162,
    "Label13_7": 163,
    "Label14": 198,
    "Label14_1": 200,
    "Label14_10": 175,
    "Label14_11": 180,
    "Label14_12": 204,
    "Label14_13": 205,
    "Label14_2": 199,
    "Label14_3": 201,
    "Label14_4": 202,
    "Label14_5": 206,
    "Label14_6": 203,
    "Label14_7": 207,
    "Label14_8": 174,
    "Label14_9": 179,
    "Label2": 143,
    "Label2_1": 211,
    "Label2_2": 109,
    "Label3": 4,
    "Label3_1": 153,
    "Label6": 156,
    "LabelsInputs": 154,
    "lbl_BackGroundLuminance_12": 98,
    "lbl_BackGroundLuminance_13": 94,
    "lbl_BackGroundLuminance_14": 93,
    "lbl_BackGroundLuminance_15": 91,
    "lbl_ContrastRatio_3": 97,
    "lbl_IconColorLuminance_3": 92,
    "lbl_IconName": 66,
    "lbl_MenuText": 240,
    "lbl_MenuText_1": 247,
    "lbl_PowerApps": 255,
    "lbl_ScreenName": 257,
    "lblIconColorOFI_10": 70,
    "lblIconColorOFI_11": 68,
    "lblIconColorOFI_46": 88,
    "lblIconColorOFI_47": 83,
    "lblIconColorOFI_48": 76,
    "lblIconColorOFI_49": 74,
    "lblIconColorOFI_50": 79,
    "lblIconColorOFI_51": 86,
    "lblIconColorOFI_9": 96,
    "lblIconImageDataOFI_4": 102,
    "lblIconNameOFI_10": 48,
    "lblIconNameOFI_11": 53,
    "lblIconNameOFI_12": 58,
    "lblIconNameOFI_3": 63,
    "lblIconNameOFI_4": 23,
    "lblIconNameOFI_5": 18,
    "lblIconNameOFI_6": 28,
    "lblIconNameOFI_7": 33,
    "lblIconNameOFI_8": 38,
    "lblIconNameOFI_9": 43,
    "lblSelectedIconOFI_26": 65,
    "Menu Builder": 0,
    "MicrosoftMenu": 164,
    "PCFCopyTextComponent2": 105,
    "PP-Header": 0,
    "PP-Header_1": 3,
    "PP-Header_2": 151,
    "PP-hIconBar": 0,
    "PP-hIconBar_1": 197,
    "PP-MainMenu": 0,
    "PP-MainMenu_1": 168,
    "PP-OfficeRail": 0,
    "PP-OfficeRail_1": 172,
    "PP-TeamsRail": 0,
    "PP-TeamsRail_1": 171,
    "PP-vIconBar": 0,
    "PP-vIconBar_1": 194,
    "Rectangle1": 107,
    "Rectangle1_1": 210,
    "Rectangle1_2": 108,
    "Rectangle2_10": 46,
    "Rectangle2_11": 51,
    "Rectangle2_12": 56,
    "Rectangle2_3": 61,
    "Rectangle2_4": 21,
    "Rectangle2_5": 16,
    "Rectangle2_6": 26,
    "Rectangle2_7": 31,
    "Rectangle2_8": 36,
    "Rectangle2_9": 41,
    "Rectangle3": 245,
    "Rectangle3_1": 250,
    "Rectangle3_2": 251,
    "Rectangle4_2": 184,
    "Rectangle4_3": 183,
    "Rectangle5": 165,
    "Rectangle6": 214,
    "Rectangle6_1": 113,
    "Rectangle7": 166,
    "Rectangle7_1": 169,
    "Rectangle8": 196,
    "Rectangle8_1": 193,
    "Screen1": 0,
    "selected_Icon": 95,
    "Slider_Background_B_3": 89,
    "Slider_Background_G_3": 84,
    "Slider_Background_R_3": 77,
    "Slider_Icon_B_3": 90,
    "Slider_Icon_G_3": 82,
    "Slider_Icon_R_3": 78,
    "TM-MainMenu_1": 7,
    "Toggle1": 232,
    "Toggle1_1": 133,
    "VS Code": 0,
    "VS Code_1": 2
  },
  "TemplateVersions": {
    "251d3182c5f14ebda0954caccc8061c6": "637556365777906212",
    "2f6fd9479bf54d6d87804e13a7a46344": "637556365777896594",
    "677fb63b9818481e87e97787923fb8da": "637556365777901089",
    "6fda9d5d46344732b503488ec8d08939": "637556365777899165",
    "8d5a6fce1ee2453e82777a553277693a": "637556365777890744",
    "9f31274f2958450c8715bd6776b635c5": "637556365777903411",
    "a437dfc8870647489d9b037db2a7427e": "637556365777879538",
    "c855490e17ba4912a20655359782e195": "637556365777904510",
    "e4882056a52441119876391294845a30": "637556365777906490"
  },
  "VolatileProperties": {
    "AnalysisLoadTime": 43.4548818,
    "ControlCount": {
      "251d3182c5f14ebda0954caccc8061c6": 2,
      "2f6fd9479bf54d6d87804e13a7a46344": 2,
      "677fb63b9818481e87e97787923fb8da": 2,
      "6fda9d5d46344732b503488ec8d08939": 3,
      "8d5a6fce1ee2453e82777a553277693a": 2,
      "9f31274f2958450c8715bd6776b635c5": 2,
      "a437dfc8870647489d9b037db2a7427e": 3,
      "arrow": 1,
      "button": 12,
      "c855490e17ba4912a20655359782e195": 3,
      "circle": 1,
      "e4882056a52441119876391294845a30": 2,
      "gallery": 20,
      "galleryTemplate": 20,
      "group": 6,
      "groupContainer": 9,
      "icon": 22,
      "image": 26,
      "label": 88,
      "raw_RAW.CanvasFileDownloader(fd140aaf-4df4-11dd-bd17-0019b9312238)": 1,
      "raw_RAW.CanvasFileUploader(fd140aaf-4df4-11dd-bd17-0019b9312238)": 1,
      "raw_RAW.ColorPicker.ColorPicker(fd140aaf-4df4-11dd-bd17-0019b9312238)": 2,
      "rectangle": 26,
      "screen": 3,
      "slider": 6,
      "tbag_CanvizLLCPCF.PCFCopyTextComponent(fd140aaf-4df4-11dd-bd17-0019b9312238)": 2,
      "text": 15,
      "toggleSwitch": 2
    },
    "DeserializationLoadTime": 10.3786057
  }
}